[
  {
    "rank": 1,
    "team": "SEA",
    "totalDVOA": 40,
    "wins": 13,
    "games": 16,
    "offenseDVOA": 9.4,
    "offenseRank": 7,
    "defenseDVOA": -25.9,
    "defenseRank": 1,
    "stDVOA": 4.7,
    "stRank": 5
  },
  {
    "rank": 2,
    "team": "DEN",
    "totalDVOA": 32.7,
    "wins": 13,
    "games": 16,
    "offenseDVOA": 33.5,
    "offenseRank": 1,
    "defenseDVOA": -0.2,
    "defenseRank": 15,
    "stDVOA": -1,
    "stRank": 21
  },
  {
    "rank": 3,
    "team": "CAR",
    "totalDVOA": 24.6,
    "wins": 12,
    "games": 16,
    "offenseDVOA": 7.9,
    "offenseRank": 10,
    "defenseDVOA": -15.7,
    "defenseRank": 3,
    "stDVOA": 1,
    "stRank": 13
  },
  {
    "rank": 4,
    "team": "NO",
    "totalDVOA": 19.3,
    "wins": 11,
    "games": 16,
    "offenseDVOA": 16,
    "offenseRank": 5,
    "defenseDVOA": -5.8,
    "defenseRank": 10,
    "stDVOA": -2.5,
    "stRank": 24
  },
  {
    "rank": 5,
    "team": "NE",
    "totalDVOA": 18.9,
    "wins": 12,
    "games": 16,
    "offenseDVOA": 16.4,
    "offenseRank": 4,
    "defenseDVOA": 4.2,
    "defenseRank": 20,
    "stDVOA": 6.7,
    "stRank": 2
  },
  {
    "rank": 6,
    "team": "KC",
    "totalDVOA": 17.5,
    "wins": 11,
    "games": 16,
    "offenseDVOA": 3,
    "offenseRank": 15,
    "defenseDVOA": -6.7,
    "defenseRank": 9,
    "stDVOA": 7.8,
    "stRank": 1
  },
  {
    "rank": 7,
    "team": "SF",
    "totalDVOA": 17.4,
    "wins": 12,
    "games": 16,
    "offenseDVOA": 9.1,
    "offenseRank": 8,
    "defenseDVOA": -4.6,
    "defenseRank": 13,
    "stDVOA": 3.7,
    "stRank": 7
  },
  {
    "rank": 8,
    "team": "PHI",
    "totalDVOA": 15.2,
    "wins": 10,
    "games": 16,
    "offenseDVOA": 22.9,
    "offenseRank": 3,
    "defenseDVOA": 4.9,
    "defenseRank": 23,
    "stDVOA": -2.8,
    "stRank": 25
  },
  {
    "rank": 9,
    "team": "CIN",
    "totalDVOA": 14.2,
    "wins": 11,
    "games": 16,
    "offenseDVOA": 0.4,
    "offenseRank": 17,
    "defenseDVOA": -12.6,
    "defenseRank": 5,
    "stDVOA": 1.2,
    "stRank": 12
  },
  {
    "rank": 10,
    "team": "ARI",
    "totalDVOA": 10,
    "wins": 10,
    "games": 16,
    "offenseDVOA": -2.4,
    "offenseRank": 20,
    "defenseDVOA": -16.4,
    "defenseRank": 2,
    "stDVOA": -4.1,
    "stRank": 27
  },
  {
    "rank": 11,
    "team": "CHI",
    "totalDVOA": 6.6,
    "wins": 8,
    "games": 16,
    "offenseDVOA": 13.3,
    "offenseRank": 6,
    "defenseDVOA": 8.7,
    "defenseRank": 25,
    "stDVOA": 2,
    "stRank": 11
  },
  {
    "rank": 12,
    "team": "SD",
    "totalDVOA": 6.4,
    "wins": 9,
    "games": 16,
    "offenseDVOA": 23.1,
    "offenseRank": 2,
    "defenseDVOA": 17.5,
    "defenseRank": 32,
    "stDVOA": 0.8,
    "stRank": 15
  },
  {
    "rank": 13,
    "team": "IND",
    "totalDVOA": 3.2,
    "wins": 11,
    "games": 16,
    "offenseDVOA": 4.3,
    "offenseRank": 13,
    "defenseDVOA": 0.9,
    "defenseRank": 16,
    "stDVOA": -0.1,
    "stRank": 18
  },
  {
    "rank": 14,
    "team": "STL",
    "totalDVOA": 2.4,
    "wins": 7,
    "games": 16,
    "offenseDVOA": -9.5,
    "offenseRank": 22,
    "defenseDVOA": -5.7,
    "defenseRank": 11,
    "stDVOA": 6.3,
    "stRank": 4
  },
  {
    "rank": 15,
    "team": "PIT",
    "totalDVOA": 0.9,
    "wins": 8,
    "games": 16,
    "offenseDVOA": 4.4,
    "offenseRank": 12,
    "defenseDVOA": 4,
    "defenseRank": 19,
    "stDVOA": 0.5,
    "stRank": 16
  },
  {
    "rank": 16,
    "team": "DET",
    "totalDVOA": -1.5,
    "wins": 7,
    "games": 16,
    "offenseDVOA": -1.9,
    "offenseRank": 19,
    "defenseDVOA": -0.8,
    "defenseRank": 14,
    "stDVOA": -0.4,
    "stRank": 20
  },
  {
    "rank": 17,
    "team": "DAL",
    "totalDVOA": -2.8,
    "wins": 8,
    "games": 16,
    "offenseDVOA": 7.5,
    "offenseRank": 11,
    "defenseDVOA": 13.8,
    "defenseRank": 30,
    "stDVOA": 3.4,
    "stRank": 8
  },
  {
    "rank": 18,
    "team": "BUF",
    "totalDVOA": -3.3,
    "wins": 6,
    "games": 16,
    "offenseDVOA": -11.5,
    "offenseRank": 25,
    "defenseDVOA": -13.8,
    "defenseRank": 4,
    "stDVOA": -5.6,
    "stRank": 30
  },
  {
    "rank": 19,
    "team": "TB",
    "totalDVOA": -5.1,
    "wins": 4,
    "games": 16,
    "offenseDVOA": -10.4,
    "offenseRank": 24,
    "defenseDVOA": -6.8,
    "defenseRank": 8,
    "stDVOA": -1.5,
    "stRank": 22
  },
  {
    "rank": 20,
    "team": "GB",
    "totalDVOA": -6,
    "wins": 8,
    "games": 16,
    "offenseDVOA": 8.6,
    "offenseRank": 9,
    "defenseDVOA": 14.4,
    "defenseRank": 31,
    "stDVOA": -0.3,
    "stRank": 19
  },
  {
    "rank": 21,
    "team": "TEN",
    "totalDVOA": -6.1,
    "wins": 7,
    "games": 16,
    "offenseDVOA": 1.4,
    "offenseRank": 16,
    "defenseDVOA": 4.2,
    "defenseRank": 22,
    "stDVOA": -3.2,
    "stRank": 26
  },
  {
    "rank": 22,
    "team": "MIA",
    "totalDVOA": -6.5,
    "wins": 8,
    "games": 16,
    "offenseDVOA": -1.8,
    "offenseRank": 18,
    "defenseDVOA": 2.4,
    "defenseRank": 17,
    "stDVOA": -2.4,
    "stRank": 23
  },
  {
    "rank": 23,
    "team": "BAL",
    "totalDVOA": -6.7,
    "wins": 8,
    "games": 16,
    "offenseDVOA": -21.7,
    "offenseRank": 30,
    "defenseDVOA": -8.7,
    "defenseRank": 7,
    "stDVOA": 6.3,
    "stRank": 3
  },
  {
    "rank": 24,
    "team": "NYJ",
    "totalDVOA": -7.7,
    "wins": 8,
    "games": 16,
    "offenseDVOA": -15.3,
    "offenseRank": 27,
    "defenseDVOA": -5.6,
    "defenseRank": 12,
    "stDVOA": 2.1,
    "stRank": 10
  },
  {
    "rank": 25,
    "team": "ATL",
    "totalDVOA": -10.4,
    "wins": 4,
    "games": 16,
    "offenseDVOA": 3.2,
    "offenseRank": 14,
    "defenseDVOA": 13.5,
    "defenseRank": 29,
    "stDVOA": -0.1,
    "stRank": 17
  },
  {
    "rank": 26,
    "team": "MIN",
    "totalDVOA": -11.4,
    "wins": 5,
    "games": 16,
    "offenseDVOA": -4.7,
    "offenseRank": 21,
    "defenseDVOA": 10.5,
    "defenseRank": 27,
    "stDVOA": 3.8,
    "stRank": 6
  },
  {
    "rank": 27,
    "team": "NYG",
    "totalDVOA": -15.7,
    "wins": 7,
    "games": 16,
    "offenseDVOA": -22,
    "offenseRank": 31,
    "defenseDVOA": -11.4,
    "defenseRank": 6,
    "stDVOA": -5.1,
    "stRank": 28
  },
  {
    "rank": 28,
    "team": "CLE",
    "totalDVOA": -21.8,
    "wins": 4,
    "games": 16,
    "offenseDVOA": -14.4,
    "offenseRank": 26,
    "defenseDVOA": 8.2,
    "defenseRank": 24,
    "stDVOA": 0.9,
    "stRank": 14
  },
  {
    "rank": 29,
    "team": "WAS",
    "totalDVOA": -26.2,
    "wins": 3,
    "games": 16,
    "offenseDVOA": -10,
    "offenseRank": 23,
    "defenseDVOA": 4.2,
    "defenseRank": 21,
    "stDVOA": -12,
    "stRank": 32
  },
  {
    "rank": 30,
    "team": "HOU",
    "totalDVOA": -26.5,
    "wins": 2,
    "games": 16,
    "offenseDVOA": -18.9,
    "offenseRank": 29,
    "defenseDVOA": 2.5,
    "defenseRank": 18,
    "stDVOA": -5.1,
    "stRank": 29
  },
  {
    "rank": 31,
    "team": "OAK",
    "totalDVOA": -34.1,
    "wins": 4,
    "games": 16,
    "offenseDVOA": -16.7,
    "offenseRank": 28,
    "defenseDVOA": 10.3,
    "defenseRank": 26,
    "stDVOA": -7.1,
    "stRank": 31
  },
  {
    "rank": 32,
    "team": "JAC",
    "totalDVOA": -38.2,
    "wins": 4,
    "games": 16,
    "offenseDVOA": -29.8,
    "offenseRank": 32,
    "defenseDVOA": 10.9,
    "defenseRank": 28,
    "stDVOA": 2.5,
    "stRank": 9
  }
]